powerfulcases/__init__.py
powerfulcases/cache.py
powerfulcases/cases.py
powerfulcases/cli.py
powerfulcases/manifest.py
powerfulcases/py.typed
powerfulcases/registry.py
powerfulcases/cases/case10ba/case10ba.m
powerfulcases/cases/case10ba/manifest.toml
powerfulcases/cases/case118zh/case118zh.m
powerfulcases/cases/case118zh/manifest.toml
powerfulcases/cases/case1197/case1197.m
powerfulcases/cases/case1197/manifest.toml
powerfulcases/cases/case12da/case12da.m
powerfulcases/cases/case12da/manifest.toml
powerfulcases/cases/case1354pegase/case1354pegase.m
powerfulcases/cases/case1354pegase/manifest.toml
powerfulcases/cases/case136ma/case136ma.m
powerfulcases/cases/case136ma/manifest.toml
powerfulcases/cases/case141/case141.m
powerfulcases/cases/case141/manifest.toml
powerfulcases/cases/case145/case145.m
powerfulcases/cases/case145/manifest.toml
powerfulcases/cases/case15da/case15da.m
powerfulcases/cases/case15da/manifest.toml
powerfulcases/cases/case15nbr/case15nbr.m
powerfulcases/cases/case15nbr/manifest.toml
powerfulcases/cases/case16am/case16am.m
powerfulcases/cases/case16am/manifest.toml
powerfulcases/cases/case16ci/case16ci.m
powerfulcases/cases/case16ci/manifest.toml
powerfulcases/cases/case17me/case17me.m
powerfulcases/cases/case17me/manifest.toml
powerfulcases/cases/case18/case18.m
powerfulcases/cases/case18/manifest.toml
powerfulcases/cases/case1888rte/case1888rte.m
powerfulcases/cases/case1888rte/manifest.toml
powerfulcases/cases/case18nbr/case18nbr.m
powerfulcases/cases/case18nbr/manifest.toml
powerfulcases/cases/case1951rte/case1951rte.m
powerfulcases/cases/case1951rte/manifest.toml
powerfulcases/cases/case22/case22.m
powerfulcases/cases/case22/manifest.toml
powerfulcases/cases/case2383wp/case2383wp.m
powerfulcases/cases/case2383wp/manifest.toml
powerfulcases/cases/case2736sp/case2736sp.m
powerfulcases/cases/case2736sp/manifest.toml
powerfulcases/cases/case2737sop/case2737sop.m
powerfulcases/cases/case2737sop/manifest.toml
powerfulcases-0.4.0.dist-info/METADATA
powerfulcases-0.4.0.dist-info/WHEEL
powerfulcases-0.4.0.dist-info/entry_points.txt
powerfulcases-0.4.0.dist-info/top_level.txt
powerfulcases-0.4.0.dist-info/RECORD
