Metadata-Version: 2.4
Name: powerfulcases
Version: 0.4.0
Summary: Test case data for power systems simulation
Author-email: Hantao Cui <cuihantao@gmail.com>
License-Expression: MIT
Project-URL: Homepage, https://github.com/cuihantao/PowerfulCases
Project-URL: Repository, https://github.com/cuihantao/PowerfulCases
Keywords: power systems,simulation,test cases,IEEE
Classifier: Development Status :: 4 - Beta
Classifier: Intended Audience :: Science/Research
Classifier: Programming Language :: Python :: 3
Classifier: Programming Language :: Python :: 3.8
Classifier: Programming Language :: Python :: 3.9
Classifier: Programming Language :: Python :: 3.10
Classifier: Programming Language :: Python :: 3.11
Classifier: Programming Language :: Python :: 3.12
Classifier: Topic :: Scientific/Engineering
Requires-Python: >=3.8
Requires-Dist: click>=8.0
Requires-Dist: toml>=0.10
Requires-Dist: tomli>=2.0; python_version < "3.11"
